pyfacy/__init__.py
pyfacy/preprocess.py
pyfacy/utils.py
pyfacy/face_clust/__init__.py
pyfacy/face_clust/algorithm.py
pyfacy/face_recog/__init__.py
pyfacy/face_recog/algorithm.py
pyfacy-1.0.1.dist-info/METADATA
pyfacy-1.0.1.dist-info/RECORD
pyfacy-1.0.1.dist-info/WHEEL
pyfacy-1.0.1.dist-info/top_level.txt
