Metadata-Version: 2.1
Name: pyfacy
Version: 1.0.1
Summary: Face Recognition with Machine Learning and Face Clustering
Home-page: https://github.com/ManivannanMurugavel/pyfacy
Author: Manivannan
Author-email: manivannanmca2012@gmail.com
License: MIT license
Keywords: pyfacy
Platform: UNKNOWN
Classifier: Programming Language :: Python :: 2
Classifier: Programming Language :: Python :: 2.6
Classifier: Programming Language :: Python :: 2.7
Classifier: Programming Language :: Python :: 3
Classifier: Programming Language :: Python :: 3.3
Classifier: Programming Language :: Python :: 3.4
Classifier: Programming Language :: Python :: 3.5
Classifier: Programming Language :: Python :: 3.6
Classifier: License :: OSI Approved :: MIT License
Classifier: Operating System :: OS Independent
